cybershbd/__init__.py
cybershbd/cybershbd.py
cybershbd-1.0.4.dist-info/METADATA
cybershbd-1.0.4.dist-info/WHEEL
cybershbd-1.0.4.dist-info/entry_points.txt
cybershbd-1.0.4.dist-info/top_level.txt
cybershbd-1.0.4.dist-info/RECORD
