Metadata-Version: 2.1
Name: cybershbd
Version: 1.0.4
Summary: CyberSH Tools Installer!
Home-page: https://github.com/ShTasrif
Author: CyberSH
Author-email: cybershbd@gmail.com
License: MIT
Keywords: cybershbd,cyber sh,cybersh tools,cybersh tools installer
Classifier: Development Status :: 4 - Beta
Classifier: Intended Audience :: Developers
Classifier: Topic :: Software Development :: Libraries :: Python Modules
Classifier: License :: OSI Approved :: MIT License
Classifier: Programming Language :: Python :: 3
Classifier: Operating System :: OS Independent
Classifier: Environment :: Console
Requires-Python: >=3.9.5
